replit/object_storage/__init__.py
replit/object_storage/_config.py
replit/object_storage/client.py
replit/object_storage/errors.py
replit/object_storage/object.py
replit_object_storage-1.0.2.dist-info/METADATA
replit_object_storage-1.0.2.dist-info/WHEEL
replit_object_storage-1.0.2.dist-info/RECORD
