Metadata-Version: 2.1
Name: replit.object_storage
Version: 1.0.2
Summary: A library for interacting with Object Storage on Replit
Home-page: https://github.com/replit/replit-object-storage-python
License: ISC
Author: Repl.it
Author-email: contact@repl.it
Requires-Python: >=3.8.0,<3.13
Classifier: License :: OSI Approved
Classifier: License :: OSI Approved :: ISC License (ISCL)
Classifier: Operating System :: OS Independent
Classifier: Programming Language :: Python :: 3
Classifier: Programming Language :: Python :: 3.8
Classifier: Programming Language :: Python :: 3.9
Classifier: Programming Language :: Python :: 3.10
Classifier: Programming Language :: Python :: 3.11
Classifier: Programming Language :: Python :: 3.12
Requires-Dist: google-cloud-storage (>=2.14.0,<3.0.0)
Requires-Dist: requests (>=2.31.0,<3.0.0)
Project-URL: Repository, https://github.com/replit/replit-object-storage-python
